ascii_art_TNH/__init__.py
ascii_art_TNH/__main__.py
ascii_art_TNH/ascii_art.py
ascii_art_TNH/gallery.py
ascii_art_TNH/noises.py
ascii_art_tnh-1.1.6.dist-info/METADATA
ascii_art_tnh-1.1.6.dist-info/WHEEL
ascii_art_tnh-1.1.6.dist-info/licenses/LICENSE
ascii_art_tnh-1.1.6.dist-info/RECORD
