Metadata-Version: 2.3
Name: Ascii_Art_TNH
Version: 1.1.6
Summary: A small silly package which prints ASCII art based on certain inputs. Watch out for the interrupting cow
Project-URL: Homepage, https://github.com/software-students-fall2024/3-python-package-tnh-tnh-needs-help?tab=readme-ov-file
Author-email: Hugo Bray <hwb4547@nyu.edu>, Tamara Bueno <tb2803@nyu.edu>, Nuzhat Bushra <ntb5562@nyu.edu>, Melanie Zhang <mz3138@nyu.edu>
License-File: LICENSE
Classifier: License :: OSI Approved :: GNU General Public License (GPL)
Classifier: Programming Language :: Python :: 3
Classifier: Programming Language :: Python :: 3.8
Classifier: Programming Language :: Python :: 3.9
Classifier: Programming Language :: Python :: 3.10
Requires-Python: >=3.8
